Hardware implementation/Scrambler/Scrambler.srcs/sources_1/new/scrambler.sv
`timescale 1ns / 1ps
//////////////////////////////////////////////////////////////////////////////////
// Company: IIT Dharwad
// Engineer: Sumanth S Raikar
// 
// Create Date: 25.08.2023 15:32:28
// Design Name: 
// Module Name: scrambler
// Project Name: 
// Target Devices: 
// Tool Versions: 
// Description: 
// 
// Dependencies: 
// 
// Revision:
// Revision 0.01 - File Created
// Additional Comments:
// 
//////////////////////////////////////////////////////////////////////////////////


module scrambler(clk, reset, enable, pr_n,pseudo_random_number);
    input logic clk;
    input logic reset;
    input logic enable; // 1- disable the scrambler, 0-enable 
    output logic pseudo_random_number;
    
    
    output logic [0:3] pr_n; 
    
    
   
    always@(posedge clk) begin
       
        if (reset&~enable) pr_n = 4'b1001;//15'b100101010000000; 
        
        else if (enable) pr_n = 4'b0000;
        
        else pr_n = {(pr_n[2]^pr_n[3]), pr_n[0:2]}; 
        
        pseudo_random_number = (pr_n[2]^pr_n[3]);
    end
    
    
    
    
    
endmodule: scrambler

Hardware implementation/Scrambler/Scrambler.srcs/sim_1/new/testbench_scrambler.sv
`timescale 1ns / 1ps
//////////////////////////////////////////////////////////////////////////////////
// Company: 
// Engineer: 
// 
// Create Date: 25.08.2023 15:44:36
// Design Name: 
// Module Name: testbench_scrambler
// Project Name: 
// Target Devices: 
// Tool Versions: 
// Description: 
// 
// Dependencies: 
// 
// Revision:
// Revision 0.01 - File Created
// Additional Comments:
// 
//////////////////////////////////////////////////////////////////////////////////


module testbench_scrambler(

    );
    
logic tb_clk;
logic tb_reset;
logic tb_enable;
logic tb_pseudo_random_number;
logic [0:3] tb_pr_n;

scrambler scrambler1(.clk(tb_clk), .reset(tb_reset),.enable(tb_enable), .pr_n(tb_pr_n),.pseudo_random_number(tb_pseudo_random_number));

initial begin
tb_clk=1'b0;
forever #1 tb_clk=~tb_clk;  
end

initial begin
    
    tb_reset = 1'b1;
    tb_enable = 1'b0;
    
    #5;
    tb_reset=1'b0;
    tb_enable=1'b0;
    
    #50;
    tb_reset=1'b0;
    tb_enable = 1'b1;
    
    #10;
    $finish();
    
end

initial begin
    $dumpfile("scrambler_dump.vcd");
    $dumpvars;
end

endmodule

Hardware implementation/Scrambler/Scrambler.sim/sim_1/behav/xsim/scrambler_dump.vcd
$date
   Wed Aug 30 14:30:57 2023
$end
$version
  2023.1
$end
$timescale
  1ps
$end
$scope module testbench_scrambler $end
$var reg 1 ! tb_clk $end
$var reg 1 " tb_reset $end
$var reg 1 # tb_enable $end
$var reg 1 $ tb_pseudo_random_number $end
$var reg 4 % tb_pr_n [3:0] $end
$scope module scrambler1 $end
$var wire 1 & clk $end
$var wire 1 ' reset $end
$var wire 1 ( enable $end
$var reg 1 $ pseudo_random_number $end
$var reg 4 % pr_n [3:0] $end
$upscope $end
$upscope $end
$enddefinitions $end
#0
$dumpvars
0!
1"
0#
x$
bx %
0&
1'
0(
$end
#1000
1!
1$
b1001 %
1&
#2000
0!
0&
#3000
1!
1&
#4000
0!
0&
#5000
1!
0"
0$
b1100 %
1&
0'
#6000
0!
0&
#7000
1!
1$
b110 %
1&
#8000
0!
0&
#9000
1!
0$
b1011 %
1&
#10000
0!
0&
#11000
1!
1$
b101 %
1&
#12000
0!
0&
#13000
1!
b1010 %
1&
#14000
0!
0&
#15000
1!
b1101 %
1&
#16000
0!
0&
#17000
1!
b1110 %
1&
#18000
0!
0&
#19000
1!
0$
b1111 %
1&
#20000
0!
0&
#21000
1!
b111 %
1&
#22000
0!
0&
#23000
1!
b11 %
1&
#24000
0!
0&
#25000
1!
1$
b1 %
1&
#26000
0!
0&
#27000
1!
0$
b1000 %
1&
#28000
0!
0&
#29000
1!
b100 %
1&
#30000
0!
0&
#31000
1!
1$
b10 %
1&
#32000
0!
0&
#33000
1!
b1001 %
1&
#34000
0!
0&
#35000
1!
0$
b1100 %
1&
#36000
0!
0&
#37000
1!
1$
b110 %
1&
#38000
0!
0&
#39000
1!
0$
b1011 %
1&
#40000
0!
0&
#41000
1!
1$
b101 %
1&
#42000
0!
0&
#43000
1!
b1010 %
1&
#44000
0!
0&
#45000
1!
b1101 %
1&
#46000
0!
0&
#47000
1!
b1110 %
1&
#48000
0!
0&
#49000
1!
0$
b1111 %
1&
#50000
0!
0&
#51000
1!
b111 %
1&
#52000
0!
0&
#53000
1!
b11 %
1&
#54000
0!
0&
#55000
1!
1#
b0 %
1&
1(
